weakincentives/__init__.py
weakincentives/budget.py
weakincentives/clock.py
weakincentives/deadlines.py
weakincentives/errors.py
weakincentives/experiment.py
weakincentives/py.typed
weakincentives/adapters/__init__.py
weakincentives/adapters/_provider_protocols.py
weakincentives/adapters/_tool_messages.py
weakincentives/adapters/config.py
weakincentives/adapters/core.py
weakincentives/adapters/deadline_utils.py
weakincentives/adapters/inner_loop.py
weakincentives/adapters/litellm.py
weakincentives/adapters/openai.py
weakincentives/adapters/provider_response.py
weakincentives/adapters/rendering.py
weakincentives/adapters/response_parser.py
weakincentives/adapters/throttle.py
weakincentives/adapters/token_usage.py
weakincentives/adapters/tool_executor.py
weakincentives/adapters/tool_spec.py
weakincentives/adapters/utilities.py
weakincentives/adapters/claude_agent_sdk/__init__.py
weakincentives/adapters/claude_agent_sdk/_async_utils.py
weakincentives/adapters/claude_agent_sdk/_bridge.py
weakincentives/adapters/claude_agent_sdk/_errors.py
weakincentives/adapters/claude_agent_sdk/_hooks.py
weakincentives/adapters/claude_agent_sdk/_task_completion.py
weakincentives/adapters/claude_agent_sdk/_transcript_collector.py
weakincentives/adapters/claude_agent_sdk/_visibility_signal.py
weakincentives/adapters/claude_agent_sdk/adapter.py
weakincentives/adapters/claude_agent_sdk/config.py
weakincentives/adapters/claude_agent_sdk/isolation.py
weakincentives/adapters/claude_agent_sdk/workspace.py
weakincentives/cli/__init__.py
weakincentives/cli/debug_app.py
weakincentives/cli/docs_metadata.py
weakincentives/cli/query.py
weakincentives/cli/wink.py
weakincentives/cli/static/app.js
weakincentives/cli/static/index.html
weakincentives/cli/static/style.css
weakincentives/contrib/__init__.py
weakincentives/contrib/mailbox/__init__.py
weakincentives/contrib/mailbox/_redis.py
weakincentives/contrib/optimizers/__init__.py
weakincentives/contrib/optimizers/workspace_digest.py
weakincentives-0.24.0.dist-info/METADATA
weakincentives-0.24.0.dist-info/WHEEL
weakincentives-0.24.0.dist-info/entry_points.txt
weakincentives-0.24.0.dist-info/licenses/LICENSE
weakincentives-0.24.0.dist-info/RECORD
