Metadata-Version: 2.4
Name: weakincentives
Version: 0.24.0
Summary: Tools for developing and optimizing side effect free background agents
Project-URL: Homepage, https://weakincentives.com/
Project-URL: Documentation, https://github.com/weakincentives/weakincentives/blob/main/guides/README.md
Project-URL: Repository, https://github.com/weakincentives/weakincentives
Project-URL: Issue Tracker, https://github.com/weakincentives/weakincentives/issues
Author-email: Andrei Savu <andrei@weakincentives.com>
License: Apache-2.0
License-File: LICENSE
Keywords: agents,ai,background-agents,optimization,side-effect-free,weak-incentives
Classifier: Development Status :: 3 - Alpha
Classifier: Intended Audience :: Developers
Classifier: Intended Audience :: Science/Research
Classifier: License :: OSI Approved :: Apache Software License
Classifier: Operating System :: OS Independent
Classifier: Programming Language :: Python :: 3
Classifier: Programming Language :: Python :: 3.12
Classifier: Programming Language :: Python :: 3.13
Classifier: Programming Language :: Python :: 3.14
Classifier: Topic :: Scientific/Engineering :: Artificial Intelligence
Classifier: Topic :: Software Development :: Libraries :: Python Modules
Classifier: Typing :: Typed
Requires-Python: >=3.12
Provides-Extra: asteval
Requires-Dist: asteval>=1.0.7; extra == 'asteval'
Provides-Extra: claude-agent-sdk
Requires-Dist: claude-agent-sdk>=0.1.15; extra == 'claude-agent-sdk'
Provides-Extra: litellm
Requires-Dist: litellm>=1.79.3; extra == 'litellm'
Provides-Extra: openai
Requires-Dist: openai>=2.8.0; extra == 'openai'
Provides-Extra: podman
Requires-Dist: podman>=5.6.0; extra == 'podman'
Provides-Extra: redis
Requires-Dist: redis>=5.0.0; extra == 'redis'
Provides-Extra: skills
Requires-Dist: pyyaml>=6.0.0; extra == 'skills'
Provides-Extra: wink
Requires-Dist: fastapi>=0.115.0; extra == 'wink'
Requires-Dist: markdown-it-py[linkify]>=4.0.0; extra == 'wink'
Requires-Dist: uvicorn>=0.30.0; extra == 'wink'
